emp_logger/__init__.py
emp_logger/setup.py
emp_logger/utl_logging.py
emp_logger-1.1.0.dist-info/LICENSE.md
emp_logger-1.1.0.dist-info/METADATA
emp_logger-1.1.0.dist-info/WHEEL
emp_logger-1.1.0.dist-info/top_level.txt
emp_logger-1.1.0.dist-info/RECORD
